{
  "circles": [
    {
      "px": 174,
      "py": 748,
      "r": 36,
      "color": "#5ef244",
      "id": 1493394858116
    },
    {
      "px": 1088,
      "py": 37,
      "r": 29,
      "color": "#65e7fc",
      "id": 1493394897200
    },
    {
      "px": 190,
      "py": 677,
      "r": 35,
      "color": "#e18078",
      "id": 1493395741212
    },
    {
      "px": 740,
      "py": 527,
      "r": 16,
      "color": "#51a8e8",
      "id": 1493395746650
    },
    {
      "px": 579,
      "py": 594,
      "r": 22,
      "color": "#56d6ff",
      "id": 1493395825573
    },
    {
      "px": 404,
      "py": 524,
      "r": 50,
      "color": "#1afad6",
      "id": 1493395828162
    },
    {
      "px": 1058,
      "py": 39,
      "r": 25,
      "color": "#31d304",
      "id": 1493395831789
    },
    {
      "px": 870,
      "py": 223,
      "r": 22,
      "color": "#9d2ae1",
      "id": 1493395832025
    },
    {
      "px": 967,
      "py": 405,
      "r": 56,
      "color": "#7638cb",
      "id": 1493395832197
    },
    {
      "px": 370,
      "py": 156,
      "r": 47,
      "color": "#6c8d50",
      "id": 1493395834390
    },
    {
      "px": 164,
      "py": 118,
      "r": 23,
      "color": "#0245c8",
      "id": 1493395834646
    },
    {
      "px": 73,
      "py": 199,
      "r": 55,
      "color": "#fdddce",
      "id": 1493395835617
    },
    {
      "px": 234,
      "py": 274,
      "r": 41,
      "color": "#52153a",
      "id": 1493395837794
    },
    {
      "px": 441,
      "py": 305,
      "r": 52,
      "color": "#5ea587",
      "id": 1493395838822
    },
    {
      "px": 587,
      "py": 271,
      "r": 15,
      "color": "#79afae",
      "id": 1493395839061
    },
    {
      "px": 371,
      "py": 358,
      "r": 99,
      "color": "#c42402",
      "id": 1493395839488
    },
    {
      "px": 487,
      "py": 740,
      "r": 95,
      "color": "#fe476d",
      "id": 1493395839901
    }
  ],
  "squares": [
    {
      "px": 733,
      "py": 222,
      "side": 41,
      "color": "#359f9d",
      "id": 1493395001646
    },
    {
      "px": 197,
      "py": 492,
      "side": 43,
      "color": "#c01e3d",
      "id": 1493395826239
    },
    {
      "px": 821,
      "py": 370,
      "side": 89,
      "color": "#fa1dbb",
      "id": 1493395832380
    },
    {
      "px": 110,
      "py": 418,
      "side": 23,
      "color": "#5eb03e",
      "id": 1493395835963
    },
    {
      "px": 492,
      "py": 358,
      "side": 79,
      "color": "#0a49e5",
      "id": 1493395839285
    },
    {
      "px": 324,
      "py": 502,
      "side": 54,
      "color": "#5467b8",
      "id": 1493395839705
    },
    {
      "px": 796,
      "py": 777,
      "side": 97,
      "color": "#4b4172",
      "id": 1493395840117
    },
    {
      "px": 761,
      "py": 512,
      "side": 69,
      "color": "#759460",
      "id": 1493395840690
    }
  ]
}